bingefriend/shows/client_tvmaze/__init__.py
bingefriend/shows/client_tvmaze/config.py
bingefriend/shows/client_tvmaze/tvmaze_api.py
bingefriend_shows_client_tvmaze-0.1.6.dist-info/LICENSE
bingefriend_shows_client_tvmaze-0.1.6.dist-info/METADATA
bingefriend_shows_client_tvmaze-0.1.6.dist-info/WHEEL
bingefriend_shows_client_tvmaze-0.1.6.dist-info/RECORD
