Metadata-Version: 2.3
Name: bingefriend-shows-client_tvmaze
Version: 0.1.6
Summary: A Python client for the TV Maze API
License: LICENSE
Author: Tom Boone
Author-email: tbc@tomboone.com
Requires-Python: >=3.11
Classifier: License :: Other/Proprietary License
Classifier: Programming Language :: Python :: 3
Classifier: Programming Language :: Python :: 3.11
Classifier: Programming Language :: Python :: 3.12
Classifier: Programming Language :: Python :: 3.13
Requires-Dist: requests (>=2.32.3,<3.0.0)
